pylebai/gripper.py
pylebai/l_master.py
pylebai/zeroconf.py
pylebai/_gripper.pyd
pylebai/_l_master.pyd
pylebai/_zeroconf.pyd
pylebai/__init__.py
pylebai-1.4.1.dist-info/DELVEWHEEL
pylebai-1.4.1.dist-info/METADATA
pylebai-1.4.1.dist-info/RECORD
pylebai-1.4.1.dist-info/top_level.txt
pylebai-1.4.1.dist-info/WHEEL
pylebai.libs/msvcp140-a4c2229bdc2a2a630acdc095b4d86008.dll
