Metadata-Version: 2.4
Name: pylebai
Version: 1.4.1
Summary: Lebai controller Python SDK
Home-page: https://github.com/lebai-robotics/lebai-sdk
Author: liufang
Author-email: liufang <liufang_robot@outlook.com>
Project-URL: Homepage, https://github.com/lebai-robotics/lebai-sdk
Project-URL: Documentation, https://lebai-robotics.github.io/lebai-sdk/
Project-URL: Repository, https://github.com/lebai-robotics/lebai-sdk
Classifier: Development Status :: 3 - Alpha
Classifier: Intended Audience :: Developers
Classifier: License :: OSI Approved :: Apache Software License
Classifier: Operating System :: POSIX :: Linux
Classifier: Operating System :: Microsoft :: Windows
Classifier: Programming Language :: Python
Classifier: Programming Language :: Python :: 3
Classifier: Programming Language :: Python :: 3.7
Classifier: Programming Language :: Python :: 3.8
Classifier: Programming Language :: Python :: 3.9
Classifier: Programming Language :: Python :: 3.10
Classifier: Programming Language :: Python :: 3.11
Classifier: Programming Language :: Python :: 3.12
Classifier: Programming Language :: Python :: 3.13
Classifier: Programming Language :: C++
Classifier: Topic :: Software Development :: Libraries :: Python Modules
Requires-Python: >=3.7
Dynamic: author
Dynamic: home-page
